usefulgram/__init__.py
usefulgram/enums/__init__.py
usefulgram/enums/const.py
usefulgram/exceptions/__init__.py
usefulgram/exceptions/exceptions.py
usefulgram/filters/__init__.py
usefulgram/filters/database_filters.py
usefulgram/filters/parse_filters.py
usefulgram/keyboard/__init__.py
usefulgram/keyboard/builder.py
usefulgram/keyboard/buttons.py
usefulgram/keyboard/rows.py
usefulgram/lazy/__init__.py
usefulgram/lazy/editor.py
usefulgram/lazy/lazy_editing.py
usefulgram/lazy/sender.py
usefulgram/middlewares/__init__.py
usefulgram/middlewares/stacker.py
usefulgram/middlewares/trottling.py
usefulgram/parsing/__init__.py
usefulgram/parsing/decode.py
usefulgram/parsing/encode.py
usefulgram/utils/__init__.py
usefulgram-0.0.0a12.dist-info/LICENSE
usefulgram-0.0.0a12.dist-info/METADATA
usefulgram-0.0.0a12.dist-info/WHEEL
usefulgram-0.0.0a12.dist-info/RECORD
