Metadata-Version: 2.1
Name: usefulgram
Version: 0.0.0a12
Summary: Like aiogram but more easy
Home-page: https://github.com/Sethis/usefulgram
License: MIT
Author: Alexandr Bortnik
Author-email: sambonsttt@gmail.com
Requires-Python: >=3.9,<4.0
Classifier: Intended Audience :: Developers
Classifier: License :: OSI Approved :: MIT License
Classifier: Operating System :: OS Independent
Classifier: Programming Language :: Python :: 3
Classifier: Programming Language :: Python :: 3.9
Classifier: Programming Language :: Python :: 3.10
Classifier: Programming Language :: Python :: 3.11
Requires-Dist: aiogram (>=3.0.0b9,<4.0.0)
Requires-Dist: cachetools (>=4.0.0,<5.0.0)
Requires-Dist: pydantic (>=2.1.0,<3.0.0)
Requires-Dist: pytz (>=2020.3,<2021.0)
Project-URL: Bug Tracker, https://github.com/Sethis/usefulgram/issues
